MANIFEST.in
README.md
long_description.md
pyproject.toml
setup.py
undr/-index_schema.json
undr/__init__.py
undr/__main__.py
undr/bibtex.py
undr/check.py
undr/configuration.py
undr/constants.py
undr/decode.py
undr/display.py
undr/exception.py
undr/formats.py
undr/install_mode.py
undr/json_index.py
undr/json_index_tasks.py
undr/path.py
undr/path_directory.py
undr/persist.py
undr/raw.py
undr/remote.py
undr/simple.py
undr/task.py
undr/undr_default.toml
undr/undr_schema.json
undr/utilities.py
undr/version.py
undr.egg-info/PKG-INFO
undr.egg-info/SOURCES.txt
undr.egg-info/dependency_links.txt
undr.egg-info/entry_points.txt
undr.egg-info/requires.txt
undr.egg-info/top_level.txt