Metadata-Version: 2.1
Name: undr
Version: 1.0.1
Summary: Download and process Neuromorphic datasets
Home-page: https://github.com/neuromorphicsystems/undr
Author: Alexandre Marcireau
Author-email: alexandre.marcireau@gmail.com
Classifier: Programming Language :: Python :: 3
Classifier: License :: OSI Approved :: GNU General Public License v3 (GPLv3)
Classifier: Operating System :: OS Independent
